hangar/__init__.py
hangar/__main__.py
hangar/_version.py
hangar/checkout.py
hangar/constants.py
hangar/context.py
hangar/diff.py
hangar/merger.py
hangar/op_state.py
hangar/optimized_utils.c
hangar/optimized_utils.cp37-win_amd64.pyd
hangar/optimized_utils.pxd
hangar/optimized_utils.pyx
hangar/remotes.py
hangar/repository.py
hangar/txnctx.py
hangar/utils.py
hangar/backends/__init__.py
hangar/backends/chunk.py
hangar/backends/hdf5_00.py
hangar/backends/hdf5_01.py
hangar/backends/lmdb_30.py
hangar/backends/lmdb_31.py
hangar/backends/numpy_10.py
hangar/backends/remote_50.py
hangar/backends/specparse.c
hangar/backends/specparse.cp37-win_amd64.pyd
hangar/backends/specparse.pyx
hangar/backends/specs.c
hangar/backends/specs.cp37-win_amd64.pyd
hangar/backends/specs.pxd
hangar/backends/specs.pyx
hangar/cli/__init__.py
hangar/cli/cli.py
hangar/cli/utils.py
hangar/columns/__init__.py
hangar/columns/column.py
hangar/columns/common.py
hangar/columns/constructors.py
hangar/columns/layout_flat.py
hangar/columns/layout_nested.py
hangar/dataloaders/__init__.py
hangar/dataloaders/common.py
hangar/dataloaders/tfloader.py
hangar/dataloaders/torchloader.py
hangar/diagnostics/__init__.py
hangar/diagnostics/ecosystem.py
hangar/diagnostics/graphing.py
hangar/diagnostics/integrity.py
hangar/external/__init__.py
hangar/external/_external.py
hangar/external/base_plugin.py
hangar/external/plugin_manager.py
hangar/mixins/__init__.py
hangar/mixins/checkout_iteration.py
hangar/mixins/datasetget.py
hangar/mixins/recorditer.py
hangar/records/__init__.py
hangar/records/column_parsers.c
hangar/records/column_parsers.cp37-win_amd64.pyd
hangar/records/column_parsers.pyx
hangar/records/commiting.py
hangar/records/hashmachine.c
hangar/records/hashmachine.cp37-win_amd64.pyd
hangar/records/hashmachine.pyx
hangar/records/hashs.py
hangar/records/heads.py
hangar/records/parsing.py
hangar/records/queries.py
hangar/records/recordstructs.c
hangar/records/recordstructs.cp37-win_amd64.pyd
hangar-0.5.2.dist-info/AUTHORS.rst
hangar-0.5.2.dist-info/LICENSE
hangar-0.5.2.dist-info/METADATA
hangar-0.5.2.dist-info/WHEEL
hangar-0.5.2.dist-info/entry_points.txt
hangar-0.5.2.dist-info/top_level.txt
hangar-0.5.2.dist-info/RECORD
