Metadata-Version: 2.1
Name: hangar
Version: 0.5.2
Summary: Hangar is version control for tensor data. Commit, branch, merge, revert, and collaborate in the data-defined software era.
Home-page: https://github.com/tensorwerk/hangar-py
Author: Richard Izzo
Author-email: rick@tensorwerk.com
Maintainer: Richard Izzo
Maintainer-email: rick@tensorwerk.com
License: Apache 2.0
Project-URL: Documentation, https://hangar-py.readthedocs.io/
Project-URL: Changelog, https://hangar-py.readthedocs.io/en/latest/changelog.html
Project-URL: Issue Tracker, https://github.com/tensorwerk/hangar-py/issues
Platform: any
Classifier: Development Status :: 4 - Beta
Classifier: Intended Audience :: Developers
Classifier: License :: OSI Approved
Classifier: Operating System :: MacOS
Classifier: Operating System :: Microsoft :: Windows
Classifier: Operating System :: POSIX :: Linux
Classifier: Operating System :: Unix
Classifier: Programming Language :: Cython
Classifier: Programming Language :: Python :: 3 :: Only
Classifier: Programming Language :: Python :: 3.6
Classifier: Programming Language :: Python :: 3.7
Classifier: Programming Language :: Python :: 3.8
Classifier: Topic :: Database
Classifier: Topic :: Scientific/Engineering
Classifier: Topic :: Software Development :: Libraries
Classifier: Topic :: Software Development :: Version Control
Classifier: Topic :: Utilities
Requires-Python: >= 3.6.0
